adminlte/__init__.py
adminlte/apps.py
adminlte/demo/__init__.py
adminlte/demo/menu.py
adminlte/demo/urls.py
adminlte/demo/views.py
adminlte/static/demo/img/AdminLTELogo.png
adminlte/static/demo/img/avatar.png
adminlte/static/demo/img/avatar04.png
adminlte/static/demo/img/avatar2.png
adminlte/static/demo/img/avatar3.png
adminlte/static/demo/img/avatar5.png
adminlte/static/demo/img/boxed-bg.jpg
adminlte/static/demo/img/boxed-bg.png
adminlte/static/demo/img/default-150x150.png
adminlte/static/demo/img/icons.png
adminlte/static/demo/img/photo1.png
adminlte/static/demo/img/photo2.png
adminlte/static/demo/img/photo3.jpg
adminlte/static/demo/img/photo4.jpg
adminlte/static/demo/img/prod-1.jpg
adminlte/static/demo/img/prod-2.jpg
adminlte/static/demo/img/prod-3.jpg
adminlte/static/demo/img/prod-4.jpg
adminlte/static/demo/img/prod-5.jpg
adminlte/static/demo/img/user1-128x128.jpg
adminlte/static/demo/img/user2-160x160.jpg
adminlte/static/demo/img/user3-128x128.jpg
adminlte/static/demo/img/user4-128x128.jpg
adminlte/static/demo/img/user5-128x128.jpg
adminlte/static/demo/img/user6-128x128.jpg
adminlte/static/demo/img/user7-128x128.jpg
adminlte/static/demo/img/user8-128x128.jpg
adminlte/static/demo/img/credit/american-express.png
adminlte/static/demo/img/credit/cirrus.png
adminlte/static/demo/img/credit/mastercard.png
adminlte/static/demo/img/credit/mestro.png
adminlte/static/demo/img/credit/paypal.png
adminlte/static/demo/img/credit/paypal2.png
adminlte/static/demo/img/credit/visa.png
adminlte/static/demo/js/demo.js
adminlte/static/demo/js/pages/dashboard.js
adminlte/static/demo/js/pages/dashboard2.js
adminlte/static/demo/js/pages/dashboard3.js
adminlte/static/demo/plugins/flot/jquery.flot.js
adminlte/static/demo/plugins/fullcalendar/LICENSE.txt
adminlte/static/demo/plugins/fullcalendar/locales-all.js
adminlte/static/demo/plugins/fullcalendar/locales-all.min.js
adminlte/static/demo/plugins/fullcalendar/main.css
adminlte/static/demo/plugins/fullcalendar/main.d.ts
django_adminlte_amigne-0.0.1.0.dist-info/LICENSE
django_adminlte_amigne-0.0.1.0.dist-info/METADATA
django_adminlte_amigne-0.0.1.0.dist-info/WHEEL
django_adminlte_amigne-0.0.1.0.dist-info/top_level.txt
django_adminlte_amigne-0.0.1.0.dist-info/RECORD
