Metadata-Version: 2.1
Name: django-adminlte-amigne
Version: 0.0.1.0
Summary: An integration of the AdminLTE template for Django
Home-page: https://github.com/amigne/django-adminlte
Author: Yann Gauteron
Author-email: yann@gauteron.xyz
License: UNKNOWN
Platform: UNKNOWN
Classifier: Development Status :: 2 - Pre-Alpha
Classifier: Environment :: Web Environment
Classifier: Framework :: Django
Classifier: Intended Audience :: Developers
Classifier: License :: OSI Approved :: MIT License
Classifier: Operating System :: OS Independent
Classifier: Programming Language :: Python
Classifier: Programming Language :: Python :: 3
Classifier: Programming Language :: Python :: 3 :: Only
Classifier: Programming Language :: Python :: 3.8
Classifier: Topic :: Software Development :: Libraries :: Python Modules
Requires-Python: >=3.8
Requires-Dist: django-menu-gauteron
